NaviNIBS_LSL_Output/.git/COMMIT_EDITMSG
NaviNIBS_LSL_Output/.git/config
NaviNIBS_LSL_Output/.git/description
NaviNIBS_LSL_Output/.git/FETCH_HEAD
NaviNIBS_LSL_Output/.git/HEAD
NaviNIBS_LSL_Output/.git/hooks/applypatch-msg.sample
NaviNIBS_LSL_Output/.git/hooks/commit-msg.sample
NaviNIBS_LSL_Output/.git/hooks/fsmonitor-watchman.sample
NaviNIBS_LSL_Output/.git/hooks/post-update.sample
NaviNIBS_LSL_Output/.git/hooks/pre-applypatch.sample
NaviNIBS_LSL_Output/.git/hooks/pre-commit.sample
NaviNIBS_LSL_Output/.git/hooks/pre-push.sample
NaviNIBS_LSL_Output/.git/hooks/pre-rebase.sample
NaviNIBS_LSL_Output/.git/hooks/pre-receive.sample
NaviNIBS_LSL_Output/.git/hooks/prepare-commit-msg.sample
NaviNIBS_LSL_Output/.git/hooks/update.sample
NaviNIBS_LSL_Output/.git/index
NaviNIBS_LSL_Output/.git/info/exclude
NaviNIBS_LSL_Output/.git/logs/HEAD
NaviNIBS_LSL_Output/.git/logs/refs/heads/main
NaviNIBS_LSL_Output/.git/logs/refs/remotes/origin/HEAD
NaviNIBS_LSL_Output/.git/logs/refs/remotes/origin/main
NaviNIBS_LSL_Output/.git/objects/00/926538e1d8d2dc1d68e993badcffe58980ed4b
NaviNIBS_LSL_Output/.git/objects/02/62d59831368fb4f21e777fa7dda0145941cee8
NaviNIBS_LSL_Output/.git/objects/0a/041280bd00a9d068f503b8ee7ce35214bd24a1
NaviNIBS_LSL_Output/.git/objects/0d/fa23ff13dfe5db8c7fe28017f461ada7beb27d
NaviNIBS_LSL_Output/.git/objects/13/64ef60e7373a457acb412e4f6cfa7ee66e3ac1
NaviNIBS_LSL_Output/.git/objects/14/f205640a22004f8f1d7d990e4da47753188f3d
NaviNIBS_LSL_Output/.git/objects/20/180d1d273a09a1eb3cbc56baa61069787f0cb2
NaviNIBS_LSL_Output/.git/objects/28/b5c9339c797750c803d95d1ace87e983595853
NaviNIBS_LSL_Output/.git/objects/2c/25614e7d588049b03b9ff3dc65e63f199bbf2a
NaviNIBS_LSL_Output/.git/objects/32/82cef61b4d7f9947aacbd7085c5866bb7bf549
NaviNIBS_LSL_Output/.git/objects/32/8f63896a7d6a6ae7b73ff1d5619af97126661f
NaviNIBS_LSL_Output/.git/objects/33/7cc5385ac599001812290d267565398f22e7d8
NaviNIBS_LSL_Output/.git/objects/3c/a24979f93a2cbaaa1a9025ba93941dcb073ef2
navinibs_lsl_output-0.1.0.dist-info/COPYING
navinibs_lsl_output-0.1.0.dist-info/COPYING.LESSER
navinibs_lsl_output-0.1.0.dist-info/METADATA
navinibs_lsl_output-0.1.0.dist-info/WHEEL
navinibs_lsl_output-0.1.0.dist-info/RECORD
