Metadata-Version: 2.1
Name: navinibs-lsl-output
Version: 0.1.0
Summary: NaviNIBS addon for streaming data out via LSL
Home-page: https://github.com/PrecisionNeuroLab/NaviNIBS
License: LGPL-3.0-only
Author: Christopher C. Cline
Author-email: chriscline@users.noreply.github.com
Requires-Python: >=3.10,<3.12
Classifier: License :: OSI Approved :: GNU Lesser General Public License v3 (LGPLv3)
Classifier: Programming Language :: Python :: 3
Classifier: Programming Language :: Python :: 3.10
Classifier: Programming Language :: Python :: 3.11
Requires-Dist: navinibs (>=0.1.5)
Project-URL: Documentation, https://precisionneurolab.github.io/navinibs-docs
Project-URL: Repository, https://github.com/PrecisionNeuroLab/NaviNIBS_LSL_Output
